setup.py
plotting_jw/Plotting_module.py
plotting_jw/__init__.py
plotting_jw.egg-info/PKG-INFO
plotting_jw.egg-info/SOURCES.txt
plotting_jw.egg-info/dependency_links.txt
plotting_jw.egg-info/not-zip-safe
plotting_jw.egg-info/top_level.txt