Metadata-Version: 1.0
Name: plotting-jw
Version: 0.1
Summary: Plotting functions
Home-page: UNKNOWN
Author: UNKNOWN
Author-email: UNKNOWN
License: UNKNOWN
Platform: UNKNOWN
